rocketx/__init__.py
rocketx/hooks/__init__.py
rocketx/hooks/base.py
rocketx/models/__init__.py
rocketx/utils/__init__.py
rocketx/utils/log/__init__.py
rocketx/utils/log/file_handler.py
rocketx/utils/log/logging_mixin.py
rocketx_core-0.1.0.dist-info/METADATA
rocketx_core-0.1.0.dist-info/WHEEL
rocketx_core-0.1.0.dist-info/RECORD
